Lab1/blackbox.v
module blackbox(w, l, f, v);
    output w;
    input  l, f, v;
    wire   w01, w14, w17, w19, w20, w28, w31, w32, w34, w35, w38, w44, w60, w65, w71, w76, w83, w89, w91, w92, w94, w95;
    or  o3(w, w17, w35, w94);
    and a49(w17, w76, w65, w20);
    not n8(w20, w34);
    and a33(w35, w65, w34, w76);
    and a9(w94, w83, w01);
    not n59(w83, w65);
    or  o13(w01, w32, w31);
    and a22(w32, w76, w34);
    and a5(w31, w71, w76);
    not n85(w71, w34);
    or  o48(w65, w28, w44, w19);
    not n86(w28, l);
    not n81(w44, f);
    not n53(w19, v);
    and a43(w34, w92, w95);
    not n52(w92, f);
    or  o23(w95, w60, w91);
    not n93(w60, v);
    and a79(w91, l, v);
    and a30(w76, w89, w14);
    not n67(w89, v);
    or  o6(w14, w38, l);
    not n45(w38, f);
endmodule // blackbox

Lab1/blackbox_tb.v
module blackbox_test;
    reg l, f, v;                           // these are inputs to "circuit under test"
                                              // use "reg" not "wire" so can assign a value
    wire w;                        // wires for the outputs of "circuit under test"

    blackbox blackbox (w, l, f, v);  // the circuit under test
    
    initial begin                             // initial = run at beginning of simulation
                                              // begin/end = associate block with initial
 
        $dumpfile("blackbox.vcd");                  // name of dump file to create
        $dumpvars(0,blackbox_test);                 // record all signals of module "sc_test" and sub-modules
                                              // remember to change "sc_test" to the correct
                                              // module name when writing your own test benches
        
        // test all four input combinations
        // remember that 2 inputs means 2^2 = 4 combinations
        // 3 inputs would mean 2^3 = 8 combinations to test, and so on
        // this is very similar to the input columns of a truth table
        l = 0; f = 0; v=0; # 10;             // set initial values and wait 10 time units
        l = 0; f = 0; v=1; # 10;             // change inputs and then wait 10 time units
        l = 0; f = 1; v=0; # 10;             // as above
        l = 0; f = 1; v=1; # 10;
 		l = 1; f = 0; v=0; # 10;
 		l = 1; f = 0; v=1; # 10;
 		l = 1; f = 1; v=0; # 10;
 		l = 1; f = 1; v=1; # 10;
 
        $finish;                              // end the simulation
    end                      
    
    initial
        $monitor("At time %2t, l = %d f = %d v = %d w = %d",
                 $time, l, f, v, w);
endmodule // blackbox_test

Lab1/blackbox.vcd
$date
	Mon Jan 22 20:57:45 2018
$end
$version
	Icarus Verilog
$end
$timescale
	1s
$end
$scope module blackbox_test $end
$var wire 1 ! w $end
$var reg 1 " f $end
$var reg 1 # l $end
$var reg 1 $ v $end
$scope module blackbox $end
$var wire 1 " f $end
$var wire 1 # l $end
$var wire 1 $ v $end
$var wire 1 ! w $end
$var wire 1 % w01 $end
$var wire 1 & w14 $end
$var wire 1 ' w17 $end
$var wire 1 ( w19 $end
$var wire 1 ) w20 $end
$var wire 1 * w28 $end
$var wire 1 + w31 $end
$var wire 1 , w32 $end
$var wire 1 - w34 $end
$var wire 1 . w35 $end
$var wire 1 / w38 $end
$var wire 1 0 w44 $end
$var wire 1 1 w60 $end
$var wire 1 2 w65 $end
$var wire 1 3 w71 $end
$var wire 1 4 w76 $end
$var wire 1 5 w83 $end
$var wire 1 6 w89 $end
$var wire 1 7 w91 $end
$var wire 1 8 w92 $end
$var wire 1 9 w94 $end
$var wire 1 : w95 $end
$upscope $end
$upscope $end
$enddefinitions $end
#0
$dumpvars
1:
09
18
07
16
05
14
03
12
11
10
1/
1.
1-
1,
0+
1*
0)
1(
0'
1&
1%
0$
0#
0"
1!
$end
#10
13
1)
0%
0!
0-
0,
0.
0:
04
0(
01
06
1$
#20
1:
0&
1(
11
16
00
08
0/
0$
1"
#30
0:
0(
01
06
1$
#40
03
1,
1.
0)
1%
1!
1-
0+
0'
1:
14
1(
11
16
10
18
1/
0*
1&
0$
0"
1#
#50
0%
0!
0,
0.
04
0(
01
17
06
1$
#60
1%
1!
1+
1'
13
1)
14
0-
1(
11
07
16
00
08
0/
0$
1"
#70
0%
0!
15
0+
0'
02
04
0(
01
17
06
1$
