Lab4/register.v
// register: A register which may be reset to an arbirary value
//
// q      (output) - Current value of register
// d      (input)  - Next value of register
// clk    (input)  - Clock (positive edge-sensitive)
// enable (input)  - Load new value? (yes = 1, no = 0)
// reset  (input)  - Asynchronous reset    (reset = 1)
//
module register(q, d, clk, enable, reset);

    output [31:0] q;
    input  [31:0] d;
    input  clk, enable, reset;

   //  Your implementation goes here
dffe d0(q[0],d[0],clk,enable,reset);
dffe d1(q[1],d[1],clk,enable,reset);
dffe d2(q[2],d[2],clk,enable,reset);
dffe d3(q[3],d[3],clk,enable,reset);
dffe d4(q[4],d[4],clk,enable,reset);
dffe d5(q[5],d[5],clk,enable,reset);
dffe d6(q[6],d[6],clk,enable,reset);
dffe d7(q[7],d[7],clk,enable,reset);
dffe d8(q[8],d[8],clk,enable,reset);
dffe d9(q[9],d[9],clk,enable,reset);
dffe d10(q[10],d[10],clk,enable,reset);
dffe d11(q[11],d[11],clk,enable,reset);
dffe d12(q[12],d[12],clk,enable,reset);
dffe d13(q[13],d[13],clk,enable,reset);
dffe d14(q[14],d[14],clk,enable,reset);
dffe d15(q[15],d[15],clk,enable,reset);
dffe d16(q[16],d[16],clk,enable,reset);
dffe d17(q[17],d[17],clk,enable,reset);
dffe d18(q[18],d[18],clk,enable,reset);
dffe d19(q[19],d[19],clk,enable,reset);
dffe d20(q[20],d[20],clk,enable,reset);
dffe d21(q[21],d[21],clk,enable,reset);
dffe d22(q[22],d[22],clk,enable,reset);
dffe d23(q[23],d[23],clk,enable,reset);
dffe d24(q[24],d[24],clk,enable,reset);
dffe d25(q[25],d[25],clk,enable,reset);
dffe d26(q[26],d[26],clk,enable,reset);
dffe d27(q[27],d[27],clk,enable,reset);
dffe d28(q[28],d[28],clk,enable,reset);
dffe d29(q[29],d[29],clk,enable,reset);
dffe d30(q[30],d[30],clk,enable,reset);
dffe d31(q[31],d[31],clk,enable,reset);
endmodule // register



// dffe: D-type flip-flop with enable
//
// q      (output) - Current value of flip flop
// d      (input)  - Next value of flip flop
// clk    (input)  - Clock (positive edge-sensitive)
// enable (input)  - Load new value? (yes = 1, no = 0)
// reset  (input)  - Asynchronous reset   (reset =  1)
//
module dffe(q, d, clk, enable, reset);
   output q;
   reg    q;
   input  d;
   input  clk, enable, reset;

   always@(reset)
     if (reset == 1'b1)
       q <= 0;

   always@(posedge clk)
     if ((reset == 1'b0) && (enable == 1'b1))
       q <= d;
endmodule // dffe

Lab4/register_tb.v
module test;
    reg       clk = 0, enable = 0, reset = 1;  // start by reseting the register file

    /* Make a regular pulsing clock with a 10 time unit period. */
    always #5 clk = !clk;

    reg [4:0] regnum;
    reg [31:0] d;

    wire [31:0] q;
    initial begin
        $dumpfile("register.vcd");
        $dumpvars(0, test);
        # 10  reset = 0;      // stop reseting the register 

          // write 88 to the register
          enable = 1;
          regnum = 2;
          d = 88;

        # 10
          // try writing to the register when its disabled
          enable = 0;
	  regnum = 2;
	  d = 89;

        // Add your own testcases here!
	# 10
	enable=0;
	reset=1;
	d=90;

	#10
	enable=1;
	reset=1;
	d=91;

	#10
	enable=1;
	reset=0;
	d=92;

        # 50 $finish;
    end
    
    initial begin
    end

    register reg1(q, d, clk, enable, reset);
   
endmodule // test

Lab4/register.vcd
$date
	Mon Feb  5 22:34:23 2018
$end
$version
	Icarus Verilog
$end
$timescale
	1s
$end
$scope module test $end
$var wire 32 ! q [31:0] $end
$var reg 1 " clk $end
$var reg 32 # d [31:0] $end
$var reg 1 $ enable $end
$var reg 5 % regnum [4:0] $end
$var reg 1 & reset $end
$scope module reg1 $end
$var wire 1 " clk $end
$var wire 32 ' d [31:0] $end
$var wire 1 $ enable $end
$var wire 1 & reset $end
$var wire 32 ( q [31:0] $end
$scope module d0 $end
$var wire 1 " clk $end
$var wire 1 ) d $end
$var wire 1 $ enable $end
$var wire 1 & reset $end
$var reg 1 * q $end
$upscope $end
$scope module d1 $end
$var wire 1 " clk $end
$var wire 1 + d $end
$var wire 1 $ enable $end
$var wire 1 & reset $end
$var reg 1 , q $end
$upscope $end
$scope module d10 $end
$var wire 1 " clk $end
$var wire 1 - d $end
$var wire 1 $ enable $end
$var wire 1 & reset $end
$var reg 1 . q $end
$upscope $end
$scope module d11 $end
$var wire 1 " clk $end
$var wire 1 / d $end
$var wire 1 $ enable $end
$var wire 1 & reset $end
$var reg 1 0 q $end
$upscope $end
$scope module d12 $end
$var wire 1 " clk $end
$var wire 1 1 d $end
$var wire 1 $ enable $end
$var wire 1 & reset $end
$var reg 1 2 q $end
$upscope $end
$scope module d13 $end
$var wire 1 " clk $end
$var wire 1 3 d $end
$var wire 1 $ enable $end
$var wire 1 & reset $end
$var reg 1 4 q $end
$upscope $end
$scope module d14 $end
$var wire 1 " clk $end
$var wire 1 5 d $end
$var wire 1 $ enable $end
$var wire 1 & reset $end
$var reg 1 6 q $end
$upscope $end
$scope module d15 $end
$var wire 1 " clk $end
$var wire 1 7 d $end
$var wire 1 $ enable $end
$var wire 1 & reset $end
$var reg 1 8 q $end
$upscope $end
$scope module d16 $end
$var wire 1 " clk $end
$var wire 1 9 d $end
$var wire 1 $ enable $end
$var wire 1 & reset $end
$var reg 1 : q $end
$upscope $end
$scope module d17 $end
$var wire 1 " clk $end
$var wire 1 ; d $end
$var wire 1 $ enable $end
$var wire 1 & reset $end
$var reg 1 < q $end
$upscope $end
$scope module d18 $end
$var wire 1 " clk $end
$var wire 1 = d $end
$var wire 1 $ enable $end
$var wire 1 & reset $end
$var reg 1 > q $end
$upscope $end
$scope module d19 $end
$var wire 1 " clk $end
$var wire 1 ? d $end
$var wire 1 $ enable $end
$var wire 1 & reset $end
$var reg 1 @ q $end
$upscope $end
$scope module d2 $end
$var wire 1 " clk $end
$var wire 1 A d $end
$var wire 1 $ enable $end
$var wire 1 & reset $end
$var reg 1 B q $end
$upscope $end
$scope module d20 $end
$var wire 1 " clk $end
$var wire 1 C d $end
$var wire 1 $ enable $end
$var wire 1 & reset $end
$var reg 1 D q $end
$upscope $end
$scope module d21 $end
$var wire 1 " clk $end
$var wire 1 E d $end
$var wire 1 $ enable $end
$var wire 1 & reset $end
$var reg 1 F q $end
$upscope $end
$scope module d22 $end
$var wire 1 " clk $end
$var wire 1 G d $end
$var wire 1 $ enable $end
$var wire 1 & reset $end
$var reg 1 H q $end
$upscope $end
$scope module d23 $end
$var wire 1 " clk $end
$var wire 1 I d $end
$var wire 1 $ enable $end
$var wire 1 & reset $end
$var reg 1 J q $end
$upscope $end
$scope module d24 $end
$var wire 1 " clk $end
$var wire 1 K d $end
$var wire 1 $ enable $end
$var wire 1 & reset $end
$var reg 1 L q $end
$upscope $end
$scope module d25 $end
$var wire 1 " clk $end
$var wire 1 M d $end
$var wire 1 $ enable $end
$var wire 1 & reset $end
$var reg 1 N q $end
$upscope $end
$scope module d26 $end
$var wire 1 " clk $end
$var wire 1 O d $end
$var wire 1 $ enable $end
$var wire 1 & reset $end
$var reg 1 P q $end
$upscope $end
$scope module d27 $end
$var wire 1 " clk $end
$var wire 1 Q d $end
$var wire 1 $ enable $end
$var wire 1 & reset $end
$var reg 1 R q $end
$upscope $end
$scope module d28 $end
$var wire 1 " clk $end
$var wire 1 S d $end
$var wire 1 $ enable $end
$var wire 1 & reset $end
$var reg 1 T q $end
$upscope $end
$scope module d29 $end
$var wire 1 " clk $end
$var wire 1 U d $end
$var wire 1 $ enable $end
$var wire 1 & reset $end
$var reg 1 V q $end
$upscope $end
$scope module d3 $end
$var wire 1 " clk $end
$var wire 1 W d $end
$var wire 1 $ enable $end
$var wire 1 & reset $end
$var reg 1 X q $end
$upscope $end
$scope module d30 $end
$var wire 1 " clk $end
$var wire 1 Y d $end
$var wire 1 $ enable $end
$var wire 1 & reset $end
$var reg 1 Z q $end
$upscope $end
$scope module d31 $end
$var wire 1 " clk $end
$var wire 1 [ d $end
$var wire 1 $ enable $end
$var wire 1 & reset $end
$var reg 1 \ q $end
$upscope $end
$scope module d4 $end
$var wire 1 " clk $end
$var wire 1 ] d $end
$var wire 1 $ enable $end
$var wire 1 & reset $end
$var reg 1 ^ q $end
$upscope $end
$scope module d5 $end
$var wire 1 " clk $end
$var wire 1 _ d $end
$var wire 1 $ enable $end
$var wire 1 & reset $end
$var reg 1 ` q $end
$upscope $end
$scope module d6 $end
$var wire 1 " clk $end
$var wire 1 a d $end
$var wire 1 $ enable $end
$var wire 1 & reset $end
$var reg 1 b q $end
$upscope $end
$scope module d7 $end
$var wire 1 " clk $end
$var wire 1 c d $end
$var wire 1 $ enable $end
$var wire 1 & reset $end
$var reg 1 d q $end
$upscope $end
$scope module d8 $end
$var wire 1 " clk $end
$var wire 1 e d $end
$var wire 1 $ enable $end
$var wire 1 & reset $end
$var reg 1 f q $end
$upscope $end
$scope module d9 $end
$var wire 1 " clk $end
$var wire 1 g d $end
$var wire 1 $ enable $end
$var wire 1 & reset $end
$var reg 1 h q $end
$upscope $end
$upscope $end
$upscope $end
$enddefinitions $end
#0
$dumpvars
0h
xg
0f
xe
0d
xc
0b
xa
0`
x_
0^
x]
0\
x[
0Z
xY
0X
xW
0V
xU
0T
xS
0R
xQ
0P
xO
0N
xM
0L
xK
0J
xI
0H
xG
0F
xE
0D
xC
0B
xA
0@
x?
0>
x=
0<
x;
0:
x9
08
x7
06
x5
04
x3
02
x1
00
x/
0.
x-
0,
x+
0*
x)
b0 (
bx '
1&
bx %
0$
bx #
0"
b0 !
$end
#5
1"
#10
0"
0&
#15
1"
#20
0)
0+
0A
1W
1]
0_
1a
0c
0e
0g
0-
0/
01
03
05
07
09
0;
0=
0?
0C
0E
0G
0I
0K
0M
0O
0Q
0S
0U
0Y
0[
0"
b1011000 #
b1011000 '
b10 %
1$
#25
1X
1^
b1011000 !
b1011000 (
1b
1"
#30
1)
0"
b1011001 #
b1011001 '
0$
#35
1"
#40
0b
0^
b0 !
b0 (
0X
0)
1+
0"
b1011010 #
b1011010 '
1&
#45
1"
#50
1)
0"
b1011011 #
b1011011 '
1$
#55
1"
#60
0)
0+
1A
0"
b1011100 #
b1011100 '
0&
#65
1B
1X
1^
b1011100 !
b1011100 (
1b
1"
