Lab3/mux.v
// output = A (when control == 0) or B (when control == 1)
module mux2(out, A, B, control);
    output out;
    input  A, B;
    input  control;
    wire   wA, wB, not_control;
         
    not n1(not_control, control);
    and a1(wA, A, not_control);
    and a2(wB, B, control);
    or  o1(out, wA, wB);
endmodule // mux2

// output = A (when control == 00) or B (when control == 01) or
//          C (when control == 10) or D (when control == 11)
module mux4(out, A, B, C, D, control);
    output      out;
    input       A, B, C, D;
    input [1:0] control;
    wire	ab,cd;

	mux2 mab(ab,A,B,control[0]);
	mux2 mcd(cd,C,D,control[0]);
	mux2 mout(out,ab,cd,control[1]);

endmodule // mux4

Lab3/logicunit.v
// 00 - AND, 01 - OR, 10 - NOR, 11 - XOR
module logicunit(out, A, B, control);
    output      out;
    input       A, B;
    input [1:0] control;
	wire w00,w01,w10,w11;
	
	and n00(w00,A,B);
	or n01(w01,A,B);
	nor n10(w10,A,B);
	xor n11(w11,A,B);

	mux4 o0(out,w00,w01,w10,w11,control);

endmodule // logicunit

Lab3/alu1.v
module full_adder(sum, cout, a, b, cin);
    output sum, cout;
    input  a, b, cin;
    wire   partial_s, partial_c1, partial_c2;

    xor x0(partial_s, a, b);
    xor x1(sum, partial_s, cin);
    and a0(partial_c1, a, b);
    and a1(partial_c2, partial_s, cin);
    or  o1(cout, partial_c1, partial_c2);
endmodule // full_adder

`define ALU_ADD    3'h2
`define ALU_SUB    3'h3
`define ALU_AND    3'h4
`define ALU_OR     3'h5
`define ALU_NOR    3'h6
`define ALU_XOR    3'h7

// 01x - arithmetic, 1xx - logic
module alu1(out, carryout, A, B, carryin, control);
    output      out, carryout;
    input       A, B, carryin;
    input [2:0] control;
	wire sum,lo,issub,realB;

    // add code here!!!
and b0(issub,control[0],control[1]);
xor b1(realB,issub,B);

full_adder fa(sum,carryout,A,realB,carryin);
logicunit logic0(lo,A,B,control[1:0]);
mux2 o1(out,sum,lo,control[2]);
   
endmodule // alu1

Lab3/alu1_tb.v
module alu1_test;
    // exhaustively test your 1-bit ALU by adapting mux4_tb.v
    // cycle through all combinations of A, B, C, D every 16 time units
    reg A = 0;
    always #1 A = !A;
    reg B = 0;
    always #2 B = !B;
    reg carryin = 0;
    always #4 carryin = !carryin;

     
    reg [2:0] control = 0;
     
    initial begin
        $dumpfile("alu1.vcd");
        $dumpvars(0, alu1_test);

        // control is initially 0
        # 16 control = 1; // wait 16 time units (why 16?) and then set it to 1
        # 16 control = 2; // wait 16 time units and then set it to 2
        # 16 control = 3; // wait 16 time units and then set it to 3
		# 16 control = 4;
		# 16 control = 5;
		# 16 control = 6;
		# 16 control = 7;
        # 16 $finish; // wait 16 time units and then end the simulation
    end

    wire out,carryout;
    alu1 a1(out, carryout, A, B, carryin, control);

    // you really should be using gtkwave instead
    /*
    initial begin
        $display("A B C D s o");
        $monitor("%d %d %d %d %d %d (at time %t)", A, B, C, D, control, out, $time);
    end
    */
endmodule

Lab3/alu1.vcd
$date
	Thu Feb  1 23:18:42 2018
$end
$version
	Icarus Verilog
$end
$timescale
	1s
$end
$scope module alu1_test $end
$var wire 1 ! out $end
$var wire 1 " carryout $end
$var reg 1 # A $end
$var reg 1 $ B $end
$var reg 1 % carryin $end
$var reg 3 & control [2:0] $end
$scope module a1 $end
$var wire 1 # A $end
$var wire 1 $ B $end
$var wire 1 % carryin $end
$var wire 3 ' control [2:0] $end
$var wire 1 ( issub $end
$var wire 1 ) realB $end
$var wire 1 * sum $end
$var wire 1 ! out $end
$var wire 1 + lo $end
$var wire 1 " carryout $end
$scope module fa $end
$var wire 1 # a $end
$var wire 1 ) b $end
$var wire 1 % cin $end
$var wire 1 " cout $end
$var wire 1 , partial_c1 $end
$var wire 1 - partial_c2 $end
$var wire 1 . partial_s $end
$var wire 1 * sum $end
$upscope $end
$scope module logic0 $end
$var wire 1 # A $end
$var wire 1 $ B $end
$var wire 2 / control [1:0] $end
$var wire 1 0 w00 $end
$var wire 1 1 w01 $end
$var wire 1 2 w10 $end
$var wire 1 3 w11 $end
$var wire 1 + out $end
$scope module o0 $end
$var wire 1 0 A $end
$var wire 1 1 B $end
$var wire 1 2 C $end
$var wire 1 3 D $end
$var wire 2 4 control [1:0] $end
$var wire 1 + out $end
$var wire 1 5 cd $end
$var wire 1 6 ab $end
$scope module mab $end
$var wire 1 0 A $end
$var wire 1 1 B $end
$var wire 1 7 control $end
$var wire 1 8 not_control $end
$var wire 1 6 out $end
$var wire 1 9 wA $end
$var wire 1 : wB $end
$upscope $end
$scope module mcd $end
$var wire 1 2 A $end
$var wire 1 3 B $end
$var wire 1 ; control $end
$var wire 1 < not_control $end
$var wire 1 5 out $end
$var wire 1 = wA $end
$var wire 1 > wB $end
$upscope $end
$scope module mout $end
$var wire 1 6 A $end
$var wire 1 5 B $end
$var wire 1 ? control $end
$var wire 1 @ not_control $end
$var wire 1 + out $end
$var wire 1 A wA $end
$var wire 1 B wB $end
$upscope $end
$upscope $end
$upscope $end
$scope module o1 $end
$var wire 1 * A $end
$var wire 1 + B $end
$var wire 1 C control $end
$var wire 1 D not_control $end
$var wire 1 ! out $end
$var wire 1 E wA $end
$var wire 1 F wB $end
$upscope $end
$upscope $end
$upscope $end
$enddefinitions $end
#0
$dumpvars
0F
0E
1D
0C
0B
0A
1@
0?
0>
1=
1<
0;
0:
09
18
07
06
15
b0 4
03
12
01
00
b0 /
0.
0-
0,
0+
0*
0)
0(
b0 '
b0 &
0%
0$
0#
0"
0!
$end
#1
1!
1E
05
1*
0=
1.
11
02
13
1#
#2
1)
0#
1$
#3
1+
0!
1A
0E
16
0*
1"
19
0.
1,
10
03
1#
#4
0+
0A
06
15
1!
0"
09
1=
1E
0,
0)
00
01
12
1*
0#
0$
1%
#5
0!
0E
1"
05
0*
1-
0=
1.
11
02
13
1#
#6
1)
0#
1$
#7
1+
1!
1A
1E
16
1*
0-
19
0.
1,
10
03
1#
#8
0+
0A
06
15
0!
0"
09
1=
0E
0,
0)
00
01
12
0*
0#
0$
0%
#9
1!
1E
05
1*
0=
1.
11
02
13
1#
#10
1)
0#
1$
#11
1+
0!
1A
0E
16
0*
1"
19
0.
1,
10
03
1#
#12
0+
0A
06
15
1!
0"
09
1=
1E
0,
0)
00
01
12
1*
0#
0$
1%
#13
0!
0E
1"
05
0*
1-
0=
1.
11
02
13
1#
#14
1)
0#
1$
#15
1+
1!
1A
1E
16
1*
0-
19
0.
1,
10
03
1#
#16
0+
0A
06
05
0!
08
0<
0"
09
0=
0E
17
1;
0,
0)
00
01
12
0*
b1 /
b1 4
0#
0$
0%
b1 &
b1 '
#17
1+
1!
1A
1E
16
15
1*
1:
1>
1.
11
02
13
1#
#18
1)
0#
1$
#19
0!
0E
05
0*
1"
0>
0.
1,
10
03
1#
#20
0+
0A
06
1!
0"
0:
1E
0,
0)
00
01
12
1*
0#
0$
1%
#21
1+
0!
1A
0E
1"
16
15
0*
1-
1:
1>
1.
11
02
13
1#
#22
1)
0#
1$
#23
1!
1E
05
1*
0-
0>
0.
1,
10
03
1#
#24
0+
0A
06
0!
0"
0:
0E
0,
0)
00
01
12
0*
0#
0$
0%
#25
1+
1!
1A
1E
16
15
1*
1:
1>
1.
11
02
13
1#
#26
1)
0#
1$
#27
0!
0E
05
0*
1"
0>
0.
1,
10
03
1#
#28
0+
0A
06
1!
0"
0:
1E
0,
0)
00
01
12
1*
0#
0$
1%
#29
1+
0!
1A
0E
1"
16
15
0*
1-
1:
1>
1.
11
02
13
1#
#30
1)
0#
1$
#31
1!
1E
05
1*
0-
0>
0.
1,
10
03
1#
#32
1B
15
1+
1=
0A
06
0!
18
1<
0@
0"
0:
0E
07
0;
1?
0,
0)
00
01
12
0*
b10 /
b10 4
0#
0$
0%
b10 &
b10 '
#33
0+
1!
0B
1E
05
1*
0=
1.
11
02
13
1#
#34
1)
0#
1$
#35
0!
0E
16
0*
1"
19
0.
1,
10
03
1#
#36
1+
1B
06
15
1!
0"
09
1=
1E
0,
0)
00
01
12
1*
0#
0$
1%
#37
0+
0!
0B
0E
1"
05
0*
1-
0=
1.
11
02
13
1#
#38
1)
0#
1$
#39
1!
1E
16
1*
0-
19
0.
1,
10
03
1#
#40
1+
1B
06
15
0!
0"
09
1=
0E
0,
0)
00
01
12
0*
0#
0$
0%
#41
0+
1!
0B
1E
05
1*
0=
1.
11
02
13
1#
#42
1)
0#
1$
#43
0!
0E
16
0*
1"
19
0.
1,
10
03
1#
#44
1+
1B
06
15
1!
0"
09
1=
1E
0,
0)
00
01
12
1*
0#
0$
1%
#45
0+
0!
0B
0E
1"
05
0*
1-
0=
1.
11
02
13
1#
#46
1)
0#
1$
#47
1!
1E
16
1*
0-
19
0.
1,
10
03
1#
#48
0+
0B
1.
06
05
1!
08
0<
0"
09
0=
1E
1(
17
1;
0,
1)
00
01
12
1*
b11 /
b11 4
0#
0$
0%
b11 &
b11 '
#49
1+
0!
1B
0E
16
15
0*
1"
1:
1>
0.
1,
11
02
13
1#
#50
0"
0,
0)
0#
1$
#51
0+
1!
0B
1E
05
1*
0>
1.
10
03
1#
#52
06
0!
0:
0E
1"
1)
00
01
12
0*
1-
0#
0$
1%
#53
1+
1!
1B
1E
16
15
1*
0-
1:
1>
0.
1,
11
02
13
1#
#54
0"
0,
0)
0#
1$
#55
0+
0!
0B
0E
1"
05
0*
1-
0>
1.
10
03
1#
#56
06
1!
0:
1E
0"
1)
00
01
12
1*
0-
0#
0$
0%
#57
1+
0!
1B
0E
16
15
0*
1"
1:
1>
0.
1,
11
02
13
1#
#58
0"
0,
0)
0#
1$
#59
0+
1!
0B
1E
05
1*
0>
1.
10
03
1#
#60
06
0!
0:
0E
1"
1)
00
01
12
0*
1-
0#
0$
1%
#61
1+
1!
1B
1E
16
15
1*
0-
1:
1>
0.
1,
11
02
13
1#
#62
0"
0,
0)
0#
1$
#63
0+
0!
0B
0E
1"
05
0*
1-
0>
1.
10
03
1#
#64
15
0.
1=
06
18
1<
1@
0:
0"
0(
07
0;
0?
0D
0)
00
01
12
0*
0-
b0 /
b0 4
1C
0#
0$
0%
b100 &
b100 '
#65
05
1*
0=
1.
11
02
13
1#
#66
1)
0#
1$
#67
1!
1F
1+
1A
16
0*
1"
19
0.
1,
10
03
1#
#68
0!
0F
0+
0A
06
15
0"
09
1=
0,
0)
00
01
12
1*
0#
0$
1%
#69
1"
05
0*
1-
0=
1.
11
02
13
1#
#70
1)
0#
1$
#71
1!
1F
1+
1A
16
1*
0-
19
0.
1,
10
03
1#
#72
0!
0F
0+
0A
06
15
0"
09
1=
0,
0)
00
01
12
0*
0#
0$
0%
#73
05
1*
0=
1.
11
02
13
1#
#74
1)
0#
1$
#75
1!
1F
1+
1A
16
0*
1"
19
0.
1,
10
03
1#
#76
0!
0F
0+
0A
06
15
0"
09
1=
0,
0)
00
01
12
1*
0#
0$
1%
#77
1"
05
0*
1-
0=
1.
11
02
13
1#
#78
1)
0#
1$
#79
1!
1F
1+
1A
16
1*
0-
19
0.
1,
10
03
1#
#80
0!
0F
0+
0A
06
05
08
0<
0"
09
0=
17
1;
0,
0)
00
01
12
0*
b1 /
b1 4
0#
0$
0%
b101 &
b101 '
#81
1!
1F
1+
1A
16
15
1*
1:
1>
1.
11
02
13
1#
#82
1)
0#
1$
#83
05
0*
1"
0>
0.
1,
10
03
1#
#84
0!
0F
0+
0A
06
0"
0:
0,
0)
00
01
12
1*
0#
0$
1%
#85
1!
1F
1+
1A
1"
16
15
0*
1-
1:
1>
1.
11
02
13
1#
#86
1)
0#
1$
#87
05
1*
0-
0>
0.
1,
10
03
1#
#88
0!
0F
0+
0A
06
0"
0:
0,
0)
00
01
12
0*
0#
0$
0%
#89
1!
1F
1+
1A
16
15
1*
1:
1>
1.
11
02
13
1#
#90
1)
0#
1$
#91
05
0*
1"
0>
0.
1,
10
03
1#
#92
0!
0F
0+
0A
06
0"
0:
0,
0)
00
01
12
1*
0#
0$
1%
#93
1!
1F
1+
1A
1"
16
15
0*
1-
1:
1>
1.
11
02
13
1#
#94
1)
0#
1$
#95
05
1*
0-
0>
0.
1,
10
03
1#
#96
1!
1B
1F
15
1+
1=
0A
06
18
1<
0@
0"
0:
07
0;
1?
0,
0)
00
01
12
0*
b10 /
b10 4
0#
0$
0%
b110 &
b110 '
#97
0!
0F
0+
0B
05
1*
0=
1.
11
02
13
1#
#98
1)
0#
1$
#99
16
0*
1"
19
0.
1,
10
03
1#
#100
1!
1F
1+
1B
06
15
0"
09
1=
0,
0)
00
01
12
1*
0#
0$
1%
#101
0!
0F
0+
0B
1"
05
0*
1-
0=
1.
11
02
13
1#
#102
1)
0#
1$
#103
16
1*
0-
19
0.
1,
10
03
1#
#104
1!
1F
1+
1B
06
15
0"
09
1=
0,
0)
00
01
12
0*
0#
0$
0%
#105
0!
0F
0+
0B
05
1*
0=
1.
11
02
13
1#
#106
1)
0#
1$
#107
16
0*
1"
19
0.
1,
10
03
1#
#108
1!
1F
1+
1B
06
15
0"
09
1=
0,
0)
00
01
12
1*
0#
0$
1%
#109
0!
0F
0+
0B
1"
05
0*
1-
0=
1.
11
02
13
1#
#110
1)
0#
1$
#111
16
1*
0-
19
0.
1,
10
03
1#
#112
0!
0F
0+
0B
1.
06
05
08
0<
0"
09
0=
1(
17
1;
0,
1)
00
01
12
1*
b11 /
b11 4
0#
0$
0%
b111 &
b111 '
#113
1!
1F
1+
1B
16
15
0*
1"
1:
1>
0.
1,
11
02
13
1#
#114
0"
0,
0)
0#
1$
#115
0!
0F
0+
0B
05
1*
0>
1.
10
03
1#
#116
06
0:
1"
1)
00
01
12
0*
1-
0#
0$
1%
#117
1!
1F
1+
1B
16
15
1*
0-
1:
1>
0.
1,
11
02
13
1#
#118
0"
0,
0)
0#
1$
#119
0!
0F
0+
0B
1"
05
0*
1-
0>
1.
10
03
1#
#120
06
0:
0"
1)
00
01
12
1*
0-
0#
0$
0%
#121
1!
1F
1+
1B
16
15
0*
1"
1:
1>
0.
1,
11
02
13
1#
#122
0"
0,
0)
0#
1$
#123
0!
0F
0+
0B
05
1*
0>
1.
10
03
1#
#124
06
0:
1"
1)
00
01
12
0*
1-
0#
0$
1%
#125
1!
1F
1+
1B
16
15
1*
0-
1:
1>
0.
1,
11
02
13
1#
#126
0"
0,
0)
0#
1$
#127
0!
0F
0+
0B
1"
05
0*
1-
0>
1.
10
03
1#
#128
06
0:
0"
1)
00
01
12
1*
0-
0#
0$
0%
